README.md
pyproject.toml
setup.py
src/imppkg/__init__.py
src/imppkg/data.json
src/imppkg/harmonic_mean.c
src/imppkg/harmonic_mean.pyx
src/imppkg/harmony.py
src/pubpypack_harmony_udny_yule.egg-info/PKG-INFO
src/pubpypack_harmony_udny_yule.egg-info/SOURCES.txt
src/pubpypack_harmony_udny_yule.egg-info/dependency_links.txt
src/pubpypack_harmony_udny_yule.egg-info/entry_points.txt
src/pubpypack_harmony_udny_yule.egg-info/requires.txt
src/pubpypack_harmony_udny_yule.egg-info/top_level.txt
test/test_harmonic_mean.py
test/test_harmony.py